{"gbDKuQgUx702LNS95RyMNg==":"mbr-1.jpg","04sx91A9OFPVfnHsr0CBug==":"mbr-2.jpg","vx1HCfMmqDU+s7Eui2JRdg==":"mbr-3.jpg","KZ9bLk9AH2ZsJ75m1vIHgA==":"mbr.png","Y3vQ9NrQmNgUekrM4H/8nA==":"mbr-3.jpeg","4jMTBEKvtHt4yLp64yJ7rQ==":"mbr-4.jpg","vlgcUSC18u1mj5K5ihrfAw==":"mbr-7.jpg","tTz86reHysGEwhEcX5uwVA==":"mbr-8.jpg","HPvps2PYs2xvCuXnWbZ9Hw==":"mbr-8.jpeg","KF+Wa3qUz9G/nA/BRqWBHw==":"mbr.jpeg","LsH5lvBYKniR4SADVP1NTQ==":"mbr-9.jpeg","xvEZoRtTpRo8PQiyUW4s5Q==":"mbr-10.jpg","IDI+CXQpTCod/TkNrC3CYQ==":"mbr.jpg","X0NkBDGMu+zd4PYMoLSDwA==":"mbr-5.jpg","wX76oSpNBIHut/EW6vVidQ==":"mbr-1.jpeg","kBWcS24dsvzugKxtOJfDkA==":"mbr-10.jpeg","yiLtjTpMQxfkFLG8CKf3TQ==":"fega-214x214.jpg","911X7bM4yT2Mobv6BsMc+g==":"background8.jpg","h21m/IEPsvvwgsa3l19rcA==":"imagen%20de%20whatsapp%202025-11-04%20a%20las%2014.56.04_5573ffc7-991x545.jpg","OZbW1fadwuQHzsub/RB79w==":"imagen%20de%20whatsapp%202025-11-04%20a%20las%2014.56.04_e656de05-661x400.jpg","u5qp6sV66LpWzwpIrSPP6g==":"imagen%20de%20whatsapp%202025-11-04%20a%20las%2014.56.06_fe47ac26-1000x451.jpg","fZNxui9knDcgRuXsS8DpuQ==":"imagen%20de%20whatsapp%202025-11-04%20a%20las%2014.55.55_1d8ad6fd-794x1161.jpg","wBEDI98zWX4UHwpS6XEQaA==":"imagen%20de%20whatsapp%202025-11-04%20a%20las%2014.56.08_b8f906ff-1600x1600.jpg","ikIh98265DM0O7c3FhAd7A==":"imagen%20de%20whatsapp%202025-11-04%20a%20las%2014.55.59_1efbe629-794x417.jpg","vSNJE81LAdORHglH1rZYyg==":"imagen%20de%20whatsapp%202025-11-04%20a%20las%2014.56.05_cec05801-794x818.jpg","3267oGE0hPfbyuuO/dKArg==":"gymdesign-1160x1121.jpg","QjTPfOp1E/5Aia06danr/g==":"lone-456x483.jpg","AF/ZCrJ4Ri9iFrG7NPxBjA==":"whatsapp%20image%202026-01-30%20at%2010.22.31%20am%20(2)-960x1280.jpg","YiE3NoC0ehXjNUWAHyRK8Q==":"whatsapp%20image%202026-01-30%20at%2010.22.40%20am%20(3)-1000x666.jpg","QWPgh6FAfXNK3I36pgd5uw==":"whatsapp%20image%202026-01-30%20at%2010.22.41%20am-1000x682.jpg","TALZBPUmtGBuHxJqLQDPDg==":"whatsapp%20image%202026-01-30%20at%2010.22.44%20am-736x981.jpg","GOTxAurTqZhc1ZWxy9bfZQ==":"whatsapp%20image%202026-01-30%20at%2010.22.59%20am-784x526.jpg","4MQGFlGtxZiqzjKE+5B5qA==":"whatsapp%20image%202026-01-30%20at%2010.22.59%20am%20(1)-676x371.jpg","XFqW80utovRCzL554oyuYg==":"whatsapp%20image%202026-01-30%20at%2010.22.59%20am%20(2)-676x386.jpg","tAxR1OOqep8eJX0NIIORAA==":"whatsapp%20image%202026-01-30%20at%2010.23.00%20am-676x371.jpg","yzd1b2YbBkne8JlAlJduPQ==":"whatsapp%2520image%25202026-01-30%2520at%252010.22.39%2520am%2520(1)-694x434.jpg","9ahXgY5DlCl1hGG2j3FAaA==":"whatsapp%2520image%25202026-01-30%2520at%252010.23.03%2520am%2520(1)-694x918.jpg","iYNHRfLnPa3P1bXI3FmXeA==":"whatsapp%2520image%25202026-01-30%2520at%252010.22.55%2520am%2520(4)-488x480.jpg","GlXGHerZClGKQpXiL3PGMA==":"whatsapp%20image%202026-01-30%20at%2010.22.39%20am%20(3)-794x584.jpg","dqiVfV9EHsE5jLyenu4TWg==":"whatsapp%20image%202026-01-30%20at%2010.22.49%20am-794x694.jpg","LquqEnClmoylR+F13o1UKQ==":"whatsapp%20image%202026-01-30%20at%2010.22.53%20am-432x553.jpg","21o8Rvi0txLqjLH+aUltow==":"whatsapp%20image%202026-01-30%20at%2010.22.55%20am%20(3)-500x500.jpg","GzyVdh/5Luop7wq4Q5QlxQ==":"whatsapp%20image%202026-01-30%20at%2010.23.01%20am%20(2)-755x451.jpg","OkupxgR7cRdZNA1kFBWYRw==":"whatsapp%20image%202026-01-30%20at%2010.22.40%20am%20(1)-536x484.jpg","FN6qMLio6eT6rAmx1O6BMQ==":"whatsapp%20image%202026-01-30%20at%2010.22.40%20am-524x530.jpg","1LB22YeUK6vljvKnQdC6cw==":"whatsapp%20image%202026-01-30%20at%2010.22.49%20am%20(2)-794x794.jpg","zpUVqkvn6bTI7bE1GV6kMw==":"whatsapp%20image%202026-01-30%20at%2010.23.02%20am%20(1)-794x455.jpg","H8cXjXn4+W1M1am66odmWg==":"whatsapp%20image%202026-01-30%20at%2010.23.04%20am%20(1)-794x794.jpg","oRykAiO0rUD++7AmPeEwUg==":"background1.jpg","n1dx+NZv3qks526xC0hZ5Q==":"background13.jpg"}